leakybucket/__init__.py
leakybucket/leakybucket_bmi.py
leakybucket/lumped_bmi.py
leakybucket/utils.py
leakybucket-0.0.1.dist-info/METADATA
leakybucket-0.0.1.dist-info/WHEEL
leakybucket-0.0.1.dist-info/licenses/LICENSE.txt
leakybucket-0.0.1.dist-info/RECORD
